mongoc.py
mongoc-0.4.dist-info/METADATA
mongoc-0.4.dist-info/WHEEL
mongoc-0.4.dist-info/entry_points.txt
mongoc-0.4.dist-info/top_level.txt
mongoc-0.4.dist-info/RECORD
